docupie/__init__.py
docupie/core/__init__.py
docupie/core/models.py
docupie/core/openai.py
docupie/core/utils.py
docupie/extractor/__init__.py
docupie/extractor/converter.py
docupie/extractor/main_extractor.py
docupie/extractor/services/__init__.py
docupie/extractor/services/extract.py
docupie/extractor/services/formatter.py
docupie/extractor/services/templates.py
docupie/extractor/templates/__init__.py
docupie/extractor/utils/__init__.py
docupie/extractor/utils/autogenerateschema.py
docupie/extractor/utils/converttotext.py
docupie/extractor/utils/converttotypeschema.py
docupie/extractor/utils/filevalidator.py
docupie/extractor/utils/generatemarkdown.py
docupie/extractor/utils/pdfvalidator.py
docupie/extractor/utils/schemavalidator.py
scripts/__init__.py
scripts/pre_install.py
tests/__init__.py
docupie-0.1.2.dist-info/LICENSE
docupie-0.1.2.dist-info/METADATA
docupie-0.1.2.dist-info/WHEEL
docupie-0.1.2.dist-info/top_level.txt
docupie-0.1.2.dist-info/RECORD
