Metadata-Version: 2.1
Name: docupie
Version: 0.1.2
Summary: An advanced document processing tool that leverages AI to extract structured data from PDFs
Home-page: https://github.com/h-amg/docupie
Author: Husam Gibreel
Author-email: husamgibreel@gmail.com
License: UNKNOWN
Platform: UNKNOWN
Requires-Python: >=3.10.4
License-File: LICENSE
Requires-Dist: pytesseract==0.3.13
Requires-Dist: Spire.Doc==13.1.0
Requires-Dist: plum-dispatch==1.7.4
Requires-Dist: openai==1.59.8
Requires-Dist: requests==2.32.3
Requires-Dist: pdf2image==1.17.0
